README.rst
setup.py
unique/__init__.py
unique/encoding.py
unique/git.py
unique/store.py
unique.egg-info/PKG-INFO
unique.egg-info/SOURCES.txt
unique.egg-info/dependency_links.txt
unique.egg-info/requires.txt
unique.egg-info/top_level.txt