Metadata-Version: 1.0
Name: unique
Version: 0.1
Summary: Unique/Primary Key Index Store for normalize objects
Home-page: http://github.io/samv/unique
Author: Sam Vilain
Author-email: sam@vilain.net
License: MIT
Platform: UNKNOWN
